LICENSE
MANIFEST.in
README.md
setup.py
tox.ini
tests/__init__.py
tests/test_cli.py
tests/test_forwarder.py
tests/test_request.py
tests/test_response.py
tests/test_response_matcher.py
tests/test_zerotest.py
tests/generator/__init__.py
tests/generator/python/__init__.py
tests/generator/python/test_render.py
tests/helper/__init__.py
tests/helper/process.py
tests/mock/__init__.py
tests/mock/mock_server.py
tests/mock/zerotest_proxy.py
tests/record/__init__.py
tests/record/test_formatter.py
tests/record/test_http_recorder.py
tests/utils/__init__.py
tests/utils/test_generator_helper.py
tests/utils/test_http_helper.py
zerotest/__init__.py
zerotest/app.py
zerotest/cli.py
zerotest/common.py
zerotest/forwarder.py
zerotest/fuzzy_matcher.py
zerotest/request.py
zerotest/response.py
zerotest/response_matcher.py
zerotest.egg-info/PKG-INFO
zerotest.egg-info/SOURCES.txt
zerotest.egg-info/dependency_links.txt
zerotest.egg-info/entry_points.txt
zerotest.egg-info/requires.txt
zerotest.egg-info/top_level.txt
zerotest/generator/__init__.py
zerotest/generator/generator.py
zerotest/generator/python/__init__.py
zerotest/generator/python/render.py
zerotest/record/__init__.py
zerotest/record/formatter.py
zerotest/record/http_recorder.py
zerotest/utils/__init__.py
zerotest/utils/data_helper.py
zerotest/utils/encode_helper.py
zerotest/utils/generator_helper.py
zerotest/utils/http_helper.py
zerotest/utils/io_helper.py
zerotest/utils/print_helper.py
zerotest/utils/queue_helper.py
zerotest/utils/url_helper.py