Metadata-Version: 1.1
Name: zerotest
Version: 1.2.1
Summary: Lazy guy's testing tool. Capture HTTP traffic and generate python integration test for your API server.
Home-page: https://github.com/jjyr/zerotest
Author: Hari Jiang
Author-email: hari.jiang@outlook.com
License: MIT
Platform: unix
Platform: linux
Platform: osx
Classifier: License :: OSI Approved :: MIT License
Classifier: Operating System :: POSIX
Classifier: Operating System :: MacOS :: MacOS X
Classifier: Programming Language :: Python :: 2
Classifier: Programming Language :: Python :: 2.7
Classifier: Programming Language :: Python :: 3
Classifier: Programming Language :: Python :: 3.3
Classifier: Programming Language :: Python :: 3.4
Classifier: Programming Language :: Python :: 3.5
Classifier: Topic :: Software Development :: Libraries
Classifier: Topic :: Software Development :: Testing
Classifier: Topic :: Utilities
